aiodictcc/wrapper.py
aiodictcc/__init__.py
aiodictcc-1.0.4.dist-info/RECORD
aiodictcc-1.0.4.dist-info/DESCRIPTION.rst
aiodictcc-1.0.4.dist-info/metadata.json
aiodictcc-1.0.4.dist-info/top_level.txt
aiodictcc-1.0.4.dist-info/METADATA
aiodictcc-1.0.4.dist-info/WHEEL
