Metadata-Version: 2.0
Name: aiodictcc
Version: 1.0.4
Summary: An asyncio-based wrapper for dict.cc
Home-page: https://github.com/ilevn/aiodictcc
Author: Nils Theres
Author-email: nilsntth@gmail.com
License: MIT
Platform: UNKNOWN
Requires-Dist: aiohttp (>=2.0.5)
Requires-Dist: lxml (==3.7.3)
